hydra/__init__.py
hydra/bootstrap.py
hydra/main.py
hydra/controllers/__init__.py
hydra/controllers/base.py
hydra/controllers/client.py
hydra/controllers/devel.py
hydra/controllers/network.py
hydra/core/__init__.py
hydra/core/exc.py
hydra/core/version.py
hydra/ext/__init__.py
hydra/helpers/__init__.py
hydra/helpers/client.py
hydra/helpers/devel.py
hydra/helpers/network.py
hydra/helpers/release.py
hydra/plugins/__init__.py
hydra/templates/__init__.py
hydra/templates/header.jinja2
hydra/templates/key-value-print.jinja2
shipchain_hydra-1.1.4.dist-info/LICENSE.md
shipchain_hydra-1.1.4.dist-info/METADATA
shipchain_hydra-1.1.4.dist-info/WHEEL
shipchain_hydra-1.1.4.dist-info/entry_points.txt
shipchain_hydra-1.1.4.dist-info/top_level.txt
shipchain_hydra-1.1.4.dist-info/RECORD
