Metadata-Version: 2.1
Name: shipchain-hydra
Version: 1.1.4
Summary: Hydra manages many heads of networks
Home-page: https://github.com/shipchain/hydra
Author: Lee Bailey
Author-email: lbailey@shipchain.io
License: Apache-2.0
Keywords: blockchain,shipchain,loomnetwork,loom,hydra
Platform: UNKNOWN
Classifier: Development Status :: 5 - Production/Stable
Classifier: Environment :: Console
Classifier: License :: OSI Approved :: Apache Software License
Classifier: Programming Language :: Python
Classifier: Programming Language :: Python :: 3
Classifier: Programming Language :: Python :: 3.6
Requires-Dist: cement (>=3.0.4)
Requires-Dist: jinja2
Requires-Dist: pyyaml (>=5.1)
Requires-Dist: colorlog
Requires-Dist: pyfiglet
Requires-Dist: colored
Requires-Dist: boto3 (>=1.9.28)
Requires-Dist: urllib3 (<1.25,>=1.20)
Requires-Dist: troposphere
Requires-Dist: paramiko
Requires-Dist: toml
Requires-Dist: libtmux
Requires-Dist: requests
Requires-Dist: distro
Requires-Dist: tqdm
